dequeai
