Metadata-Version: 2.1
Name: dequeai
Version: 0.8230
Summary: Python Package for DEQUE AI Platform
Home-page: https://dequeapp-deque.gitbook.io/deque-docs/getting-started/dequeai-experiment-tracking
Author: The DEQUE AI Team
Author-email: team@deque.app
License: UNKNOWN
Keywords: dequeai client for deep learning
Platform: UNKNOWN
